magith/__init__.py
magith/data_proxy.py
magith/http_client.py
magith/upass.py
magith-0.0.1.dist-info/LICENSE
magith-0.0.1.dist-info/METADATA
magith-0.0.1.dist-info/WHEEL
magith-0.0.1.dist-info/top_level.txt
magith-0.0.1.dist-info/RECORD
