Metadata-Version: 2.1
Name: magith
Version: 0.0.1
Summary: magith
Home-page: https://github.com/pypa/sampleproject
Author: magith author
Author-email: magither <python@magith.com>
Classifier: Programming Language :: Python :: 3
Classifier: License :: OSI Approved :: GNU General Public License v3 (GPLv3)
Classifier: Operating System :: OS Independent
Requires-Python: >=3.6
License-File: LICENSE
Requires-Dist: magith
